autoRSA/__init__.py
autoRSA-0.0.6.dist-info/LICENSE
autoRSA-0.0.6.dist-info/METADATA
autoRSA-0.0.6.dist-info/WHEEL
autoRSA-0.0.6.dist-info/top_level.txt
autoRSA-0.0.6.dist-info/RECORD
