Metadata-Version: 2.1
Name: autoRSA
Version: 0.0.6
Summary: A package for RSA
Author: Wu Xinyuan
Author-email: 1210011033@i.smu.edu.cn
Classifier: Programming Language :: Python :: 3
Classifier: License :: OSI Approved :: MIT License
Classifier: Operating System :: OS Independent
License-File: LICENSE
Requires-Dist: open3d (==0.15.2)
Requires-Dist: numpy (==1.21.5)
Requires-Dist: tqdm (==4.64.0)
Requires-Dist: pyvista (==0.36.1)
